pydemography/__init__.py
pydemography/main.py
pydemography-0.1.2.dist-info/METADATA
pydemography-0.1.2.dist-info/WHEEL
pydemography-0.1.2.dist-info/top_level.txt
pydemography-0.1.2.dist-info/RECORD
