Metadata-Version: 2.1
Name: pydemography
Version: 0.1.2
Requires-Dist: numpy (>=1.26.3)
Requires-Dist: pandas (>=2.2.0)
Requires-Dist: seaborn (>=0.13.1)
Requires-Dist: matplotlib (>=3.8.2)
Requires-Dist: patsy (>=0.5.6)
Requires-Dist: statsmodels (>=0.14.1)
Requires-Dist: scipy (>=1.12.0)
